pyamtb/__init__.py
pyamtb/check_distance.py
pyamtb/cli.py
pyamtb/parameters.py
pyamtb/read_datas.py
pyamtb/sk_extension.py
pyamtb/tbparas.toml
pyamtb/tbparas_template.toml
pyamtb/tight_binding_model.py
pyamtb-0.2.0.dist-info/licenses/LICENSE
tests/__init__.py
pyamtb-0.2.0.dist-info/METADATA
pyamtb-0.2.0.dist-info/WHEEL
pyamtb-0.2.0.dist-info/entry_points.txt
pyamtb-0.2.0.dist-info/top_level.txt
pyamtb-0.2.0.dist-info/RECORD
