Metadata-Version: 2.4
Name: pyamtb
Version: 0.2.0
Summary: A tight-binding model package for altermagnets
Home-page: https://github.com/ooteki-teo/pyamtb
Author: Yu Xie
Author-email: Wang Dinghui <wangdh@cumt.edu.cn>, Junting Zhang <juntingzhang@cumt.edu.cn>
License-Expression: MIT
Classifier: Programming Language :: Python :: 3
Classifier: Operating System :: OS Independent
Classifier: Development Status :: 3 - Alpha
Classifier: Intended Audience :: Science/Research
Classifier: Topic :: Scientific/Engineering :: Physics
Requires-Python: >=3.7
License-File: LICENSE
Requires-Dist: numpy
Requires-Dist: matplotlib
Requires-Dist: pythtb
Provides-Extra: dev
Requires-Dist: pytest>=6.0; extra == "dev"
Requires-Dist: pytest-cov>=2.0; extra == "dev"
Requires-Dist: black>=21.0; extra == "dev"
Requires-Dist: flake8>=3.9; extra == "dev"
Dynamic: home-page
Dynamic: license-file
Dynamic: requires-python
